omnicon_genericddsengine_py/libOmniCon-GenericDDSEngine.so
omnicon_genericddsengine_py/libOmniCon_GenericDDSEngine.cpython-310-x86_64-linux-gnu.so
omnicon_genericddsengine_py/__init__.py
omnicon_genericddsengine_py/_omnicon_genericddsengine_py.cpython-310-x86_64-linux-gnu.so
omnicon_genericddsengine_py.libs/libibverbs-1de1263b.so.1.14.48.0
omnicon_genericddsengine_py.libs/libselinux-64a010fa.so.1
omnicon_genericddsengine_py.libs/libpcap-2b6f73a4.so.1.9.1
omnicon_genericddsengine_py.libs/libpcre2-8-516f4c9d.so.0.7.1
omnicon_genericddsengine_py.libs/libmount-ec61bd71.so.1.1.0
omnicon_genericddsengine_py.libs/libOmniCon-GenericDDSEngine-c2ecd69e.so
omnicon_genericddsengine_py.libs/libudev-0e908c30.so.1.6.11
omnicon_genericddsengine_py.libs/libblkid-a9167753.so.1.1.0
omnicon_genericddsengine_py.libs/libnl-route-3-3ad497a3.so.200.26.0
omnicon_genericddsengine_py.libs/libnl-3-47cd035c.so.200.26.0
omnicon_genericddsengine_py.libs/libuuid-95b83d40.so.1.3.0
omnicon_genericddsengine_py-4.7.1.post7.dist-info/WHEEL
omnicon_genericddsengine_py-4.7.1.post7.dist-info/LICENSE
omnicon_genericddsengine_py-4.7.1.post7.dist-info/RECORD
omnicon_genericddsengine_py-4.7.1.post7.dist-info/top_level.txt
omnicon_genericddsengine_py-4.7.1.post7.dist-info/METADATA
