Metadata-Version: 2.1
Name: omnicon-genericddsengine-py
Version: 4.7.1.post7
Summary: Omnicon Generic DDS Engine Python API
Home-page: https://www.OmniconSystems.com
Author: Omnicon Distributed Systems LTD
Author-email: Gal@OmniconSystems.com
Classifier: License :: Other/Proprietary License
Classifier: Operating System :: Microsoft :: Windows
Classifier: Operating System :: POSIX :: Linux
Requires-Python: >3.9, <3.13
License-File: LICENSE
